[
  {"id":"christie2011encyclopedia","author":[{"family":"Christie","given":"Daniel J."}],"citation-key":"christie2011encyclopedia","event-place":"Malden, MA","ISBN":"978-1-4051-9644-4","issued":{"date-parts":[[2011,12]]},"publisher":"Wiley","publisher-place":"Malden, MA","title":"The Encyclopedia of Peace Psychology","type":"book"},
  {"id":"hasegawa2020hajimete","author":[{"family":"長谷川","given":"寿一"},{"family":"東條","given":"正城"},{"family":"大島","given":"尚"},{"family":"丹野","given":"義彦"},{"family":"廣中","given":"直行"}],"citation-key":"hasegawa2020hajimete","curator":[{"family":"Hasegawa","given":"Toshikazu"},{"family":"Tojo","given":"Masaki"},{"family":"Ohshima","given":"Takashi"},{"family":"Tanno","given":"Yoshihiko"},{"family":"Hironaka","given":"Naoyuki"}],"edition":"3","executive-producer":[{"family":"長谷川他"}],"issued":{"date-parts":[[2020,10,28]]},"publisher":"有斐閣","title":"はじめて出会う心理学","type":"book"},
  {"id":"hayashi2015literacy","author":[{"family":"林","given":"創"},{"family":"山田","given":"剛史"}],"citation-key":"hayashi2015literacy","container-title":"日本教育心理学会第57回総会発表論文集","curator":[{"family":"Hayashi","given":"Hajimu"},{"family":"Ymada","given":"Tsuyoshi"}],"executive-producer":[{"family":"林・山田"}],"issued":{"date-parts":[[2015]]},"page":"611","title":"学術論文の読みを通したリサーチリテラシー育成の試み","type":"paper-conference"},
  {"id":"ishii2016measuring","author":[{"family":"Ishii","given":"Keiko"},{"family":"Eisen","given":"Charis"}],"citation-key":"ishii2016measuring","container-title":"Emotion measurement","editor":[{"family":"Meiselman","given":"Herbert L."}],"ISBN":"978-0-08-100508-8","issued":{"date-parts":[[2016,1]]},"page":"629–644","publisher":"Woodhead Publishing","title":"Measuring and understanding emotions in east asia","type":"chapter"},
  {"id":"lopez-corvo2009woman","author":[{"family":"Lopez-Corvo","given":"Rafael E."}],"citation-key":"lopez-corvo2009woman","compiler":[{"family":"ロペス-コルヴォ","given":"R. E."}],"dimensions":"内なる女性──女性性に関する精神分析的小論──","executive-producer":[{"family":"井上"}],"guest":[{"family":"井上","given":"果子"}],"host":[{"family":"飯野","given":"晴子"},{"family":"赤木","given":"里奈"},{"family":"山田","given":"一子"}],"ISBN":"978-0-367-10634-8","issued":{"date-parts":[[2009]]},"jurisdiction":"星和書店","publisher":"Routledge","submitted":{"date-parts":[["2014"]]},"title":"The Woman Within: A Psychoanalytic Essay on Femininity","title-short":"The Woman Within","type":"book"},
  {"id":"rosen2015wiley","author":[{"family":"Rosen","given":"Larry D."},{"family":"Cheever","given":"Nancy"},{"family":"Carrier","given":"L. Mark"}],"citation-key":"rosen2015wiley","event-place":"Chichester, West Sussex Malden, MA","ISBN":"978-1-118-77202-7","issued":{"date-parts":[[2015,6]]},"publisher":"Wiley","publisher-place":"Chichester, West Sussex Malden, MA","title":"The Wiley Blackwell Handbook of Psychology, Technology, and Society","type":"book"}
]
